setup.py
geo/__init__.py
geo/locator.py
mygmap.egg-info/PKG-INFO
mygmap.egg-info/SOURCES.txt
mygmap.egg-info/dependency_links.txt
mygmap.egg-info/requires.txt
mygmap.egg-info/top_level.txt