Metadata-Version: 1.1
Name: mygmap
Version: 1.0.2
Summary: A small wrapper around google maps api
Home-page: https://github.com/nikhilkumarsingh/mygmap
Author: Nikhil Kumar Singh
Author-email: nikhilksingh97@gmail.com
License: MIT
Keywords: maps location address
Platform: UNKNOWN
Classifier: Development Status :: 4 - Beta
Classifier: Intended Audience :: Developers
Classifier: Topic :: Internet
Classifier: License :: OSI Approved :: MIT License
Classifier: Programming Language :: Python
Classifier: Programming Language :: Python :: 2
Classifier: Programming Language :: Python :: 2.6
Classifier: Programming Language :: Python :: 2.7
Classifier: Programming Language :: Python :: 3
Classifier: Programming Language :: Python :: 3.3
Classifier: Programming Language :: Python :: 3.4
Classifier: Programming Language :: Python :: 3.5
